kagglerun/__init__.py
kagglerun/cli.py
kagglerun/executor.py
kagglerun/mcp_server.py
kagglerun-0.3.5.dist-info/METADATA
kagglerun-0.3.5.dist-info/WHEEL
kagglerun-0.3.5.dist-info/entry_points.txt
kagglerun-0.3.5.dist-info/licenses/LICENSE
kagglerun-0.3.5.dist-info/RECORD
