Metadata-Version: 2.4
Name: kagglerun
Version: 0.3.5
Summary: Execute Python on Kaggle's FREE GPUs (T4/P100/H100) from your terminal. Perfect for AI agents.
Project-URL: Homepage, https://github.com/Letemoin/kagglerun
Project-URL: Documentation, https://github.com/Letemoin/kagglerun#readme
Project-URL: Repository, https://github.com/Letemoin/kagglerun
Project-URL: Issues, https://github.com/Letemoin/kagglerun/issues
Project-URL: Changelog, https://github.com/Letemoin/kagglerun/releases
Author: KaggleRun Contributors
License: MIT
License-File: LICENSE
Keywords: ai-agents,claude,cli,deep-learning,gpu,h100,jupyter,kaggle,machine-learning,mcp,remote-execution
Classifier: Development Status :: 4 - Beta
Classifier: Environment :: Console
Classifier: Intended Audience :: Developers
Classifier: Intended Audience :: Science/Research
Classifier: License :: OSI Approved :: MIT License
Classifier: Operating System :: OS Independent
Classifier: Programming Language :: Python :: 3
Classifier: Programming Language :: Python :: 3.8
Classifier: Programming Language :: Python :: 3.9
Classifier: Programming Language :: Python :: 3.10
Classifier: Programming Language :: Python :: 3.11
Classifier: Programming Language :: Python :: 3.12
Classifier: Topic :: Scientific/Engineering :: Artificial Intelligence
Classifier: Topic :: Software Development :: Libraries :: Python Modules
Classifier: Topic :: System :: Distributed Computing
Requires-Python: >=3.8
Requires-Dist: requests>=2.25.0
Requires-Dist: websocket-client>=1.0.0
Provides-Extra: all
Requires-Dist: black>=23.0.0; extra == 'all'
Requires-Dist: mcp>=0.1.0; extra == 'all'
Requires-Dist: pytest-asyncio>=0.21.0; extra == 'all'
Requires-Dist: pytest-cov>=4.0.0; extra == 'all'
Requires-Dist: pytest>=7.0.0; extra == 'all'
Requires-Dist: ruff>=0.1.0; extra == 'all'
Provides-Extra: dev
Requires-Dist: black>=23.0.0; extra == 'dev'
Requires-Dist: pytest-asyncio>=0.21.0; extra == 'dev'
Requires-Dist: pytest-cov>=4.0.0; extra == 'dev'
Requires-Dist: pytest>=7.0.0; extra == 'dev'
Requires-Dist: ruff>=0.1.0; extra == 'dev'
Provides-Extra: mcp
Requires-Dist: mcp>=0.1.0; extra == 'mcp'
